{
  "project_info": {
    "project_number": "813163488203",
    "firebase_url": "https://spend-log-v1-default-rtdb.asia-southeast1.firebasedatabase.app",
    "project_id": "spend-log-v1",
    "storage_bucket": "spend-log-v1.appspot.com"
  },
  "client": [
    {
      "client_info": {
        "mobilesdk_app_id": "1:813163488203:android:af0041c1361c9fe79a8c4e",
        "android_client_info": {
          "package_name": "com.app.spendlog"
        }
      },
      "oauth_client": [
        {
          "client_id": "813163488203-8q406a99rpl9vnpf3vpf9s9jchp6u8q9.apps.googleusercontent.com",
          "client_type": 3
        }
      ],
      "api_key": [
        {
          "current_key": "AIzaSyDQTeDDi5m1IOmtxk16AWg9tn57tI2z7no"
        }
      ],
      "services": {
        "appinvite_service": {
          "other_platform_oauth_client": [
            {
              "client_id": "813163488203-8q406a99rpl9vnpf3vpf9s9jchp6u8q9.apps.googleusercontent.com",
              "client_type": 3
            }
          ]
        }
      }
    }
  ],
  "configuration_version": "1"
}